scrappah/__init__.py
scrappah/__version__.py
scrappah/cli.py
scrappah/downloader.py
scrappah/extractor.py
scrappah/models.py
scrappah/pipeline.py
scrappah/py.typed
scrappah/storage.py
scrappah/sync.py
scrappah/transcriber.py
scrappah-0.2.0.dist-info/METADATA
scrappah-0.2.0.dist-info/WHEEL
scrappah-0.2.0.dist-info/entry_points.txt
scrappah-0.2.0.dist-info/licenses/LICENSE
scrappah-0.2.0.dist-info/RECORD
