Metadata-Version: 2.4
Name: scrappah
Version: 0.2.0
Summary: Video dataset toolkit for research - download, extract frames, and transcribe
Project-URL: Homepage, https://github.com/yourusername/scrappah
Project-URL: Documentation, https://github.com/yourusername/scrappah#readme
Project-URL: Repository, https://github.com/yourusername/scrappah
Project-URL: Changelog, https://github.com/yourusername/scrappah/blob/main/CHANGELOG.md
Project-URL: Bug Tracker, https://github.com/yourusername/scrappah/issues
Author: Scrappah Contributors
License: MIT
License-File: LICENSE
Keywords: dataset,deep-learning,frame-extraction,machine-learning,research,scraper,transcription,video,whisper,youtube,yt-dlp
Classifier: Development Status :: 4 - Beta
Classifier: Environment :: Console
Classifier: Intended Audience :: Developers
Classifier: Intended Audience :: Science/Research
Classifier: License :: OSI Approved :: MIT License
Classifier: Operating System :: OS Independent
Classifier: Programming Language :: Python :: 3
Classifier: Programming Language :: Python :: 3.11
Classifier: Programming Language :: Python :: 3.12
Classifier: Programming Language :: Python :: 3.13
Classifier: Topic :: Multimedia :: Video
Classifier: Topic :: Scientific/Engineering :: Artificial Intelligence
Classifier: Topic :: Scientific/Engineering :: Image Processing
Classifier: Typing :: Typed
Requires-Python: >=3.11
Requires-Dist: aiosqlite>=0.19.0
Requires-Dist: numba>=0.60.0
Requires-Dist: numpy>=1.24.0
Requires-Dist: openai-whisper>=20240930
Requires-Dist: opencv-python>=4.8
Requires-Dist: pillow>=10.0
Requires-Dist: pydantic>=2.5.0
Requires-Dist: rich>=13.7.0
Requires-Dist: typer>=0.9.0
Requires-Dist: yt-dlp>=2024.1.0
Provides-Extra: decord
Requires-Dist: decord>=0.6; extra == 'decord'
Provides-Extra: dev
Requires-Dist: mypy>=1.13; extra == 'dev'
Requires-Dist: pytest-asyncio>=0.23.0; extra == 'dev'
Requires-Dist: pytest-cov>=6.0; extra == 'dev'
Requires-Dist: pytest>=8.0; extra == 'dev'
Requires-Dist: ruff>=0.8; extra == 'dev'
